{
  "build_name": "rocky-9",
  "distro_name": "rocky",
  "ssh_username": "rocky",
  "os_display_name": "Rocky 9.2",
  "guest_os_type": "linux-64",
  "firmware": "/usr/share/edk2.git/ovmf-x64/OVMF_CODE-pure-efi.fd",
  "iso_url": "https://dl.rockylinux.org/pub/rocky/9/images/x86_64/Rocky-9-GenericCloud-Base-9.2-20230513.0.x86_64.qcow2",
  "iso_checksum": "50510f98abe1b20a548102a05a9be83153b0bf634fc502d5c8d1f508f6de1430",
  "iso_checksum_type": "sha256",
  "shutdown_command": "shutdown -P now",
  "ansible_python_interpreter": "/usr/bin/python3",
  "qemu_img_args": {
    "resize": ["--shrink"]
  }
}
